hangul_utils/__init__.py
hangul_utils/preprocess.py
hangul_utils/run.py
hangul_utils/unicode.py
hangul_utils-0.4.5.dist-info/LICENSE
hangul_utils-0.4.5.dist-info/METADATA
hangul_utils-0.4.5.dist-info/WHEEL
hangul_utils-0.4.5.dist-info/dependency_links.txt
hangul_utils-0.4.5.dist-info/entry_points.txt
hangul_utils-0.4.5.dist-info/top_level.txt
hangul_utils-0.4.5.dist-info/RECORD
