Metadata-Version: 2.1
Name: hangul-utils
Version: 0.4.5
Summary: An integrated library for Korean preprocessing.
Home-page: https://github.com/kaniblu/hangul-utils
Author: Kang Min Yoo
Author-email: kaniblurous@gmail.com
License: GPL
Keywords: hangul-utils,morphological analyzer,morphology,analyzer,korean,tokenizer,sentence tokenizer,word tokenizer,pos tagger,natural language processing,jamo,korean character
Platform: Operating System :: MacOS :: MacOS X
Platform: Operating System :: POSIX :: Linux
Classifier: Environment :: Console
Classifier: Intended Audience :: Developers
Classifier: Intended Audience :: Science/Research
Classifier: Natural Language :: Korean
Classifier: Programming Language :: Java
Classifier: Programming Language :: Python
Classifier: Topic :: Software Development :: Libraries :: Python Modules
Classifier: Topic :: Text Processing :: Linguistic
Requires-Dist: tqdm
Requires-Dist: six
Requires-Dist: mecab-python (==0.996-ko-0.9.2)
Requires-Dist: map-async (>=1.2.3)
Requires-Dist: jpype1 ; python_version <= "2.7"
Requires-Dist: jpype1-py3 ; python_version >= "3.5"
